MANIFEST.in
setup.py
gloTK/__init__.py
gloTK/libseq.py
gloTK/merparse.py
gloTK/merrunanalyzer.py
gloTK/utils.py
gloTK/wrappers.py
gloTK/wrappers_biolite.py
gloTK.egg-info/PKG-INFO
gloTK.egg-info/SOURCES.txt
gloTK.egg-info/dependency_links.txt
gloTK.egg-info/entry_points.txt
gloTK.egg-info/not-zip-safe
gloTK.egg-info/requires.txt
gloTK.egg-info/top_level.txt
gloTK/scripts/__init__.py
gloTK/scripts/glotk_mitoshaper.py
gloTK/scripts/glotk_project.py
gloTK/scripts/glotk_sweep.py
gloTK/tests/ksweep_test.config