Metadata-Version: 1.1
Name: gloTK
Version: 0.1.15
Summary: Genomes of Luminous Organisms Toolkit
Home-page: https://github.com/cypridina/gloTK
Author: Darrin Schultz
Author-email: dschultz@mbari.org
License: GPLv3
Platform: UNKNOWN
Classifier: Development Status :: 2 - Pre-Alpha
Classifier: License :: OSI Approved :: GNU General Public License v3 (GPLv3)
Classifier: Programming Language :: Python :: 3
Classifier: Programming Language :: Python :: 3.5
Classifier: Operating System :: POSIX :: Linux
Classifier: Topic :: Scientific/Engineering :: Bio-Informatics
Classifier: Intended Audience :: Science/Research
Provides: gloTK
